streamrip/__init__.py
streamrip/client/__init__.py
streamrip/client/client.py
streamrip/client/deezer.py
streamrip/client/downloadable.py
streamrip/client/qobuz.py
streamrip/client/soundcloud.py
streamrip/client/tidal.py
streamrip/config.py
streamrip/config.toml
streamrip/console.py
streamrip/converter.py
streamrip/db.py
streamrip/exceptions.py
streamrip/filepath_utils.py
streamrip/media/__init__.py
streamrip/media/album.py
streamrip/media/artist.py
streamrip/media/artwork.py
streamrip/media/label.py
streamrip/media/media.py
streamrip/media/playlist.py
streamrip/media/semaphore.py
streamrip/media/track.py
streamrip/metadata/__init__.py
streamrip/metadata/album.py
streamrip/metadata/artist.py
streamrip/metadata/covers.py
streamrip/metadata/label.py
streamrip/metadata/playlist.py
streamrip/metadata/search_results.py
streamrip/metadata/tagger.py
streamrip/metadata/track.py
streamrip/metadata/util.py
streamrip/progress.py
streamrip/rip/__init__.py
streamrip/rip/cli.py
streamrip/rip/main.py
streamrip/rip/parse_url.py
streamrip/rip/prompter.py
streamrip/rip/user_paths.py
streamrip-2.0.5.dist-info/LICENSE
streamrip-2.0.5.dist-info/METADATA
streamrip-2.0.5.dist-info/WHEEL
streamrip-2.0.5.dist-info/entry_points.txt
streamrip-2.0.5.dist-info/RECORD
