Metadata-Version: 2.1
Name: streamrip
Version: 2.0.5
Summary: A fast, all-in-one music ripper for Qobuz, Deezer, Tidal, and SoundCloud
Home-page: https://github.com/nathom/streamrip
License: GPL-3.0-only
Keywords: hi-res,free,music,download
Author: nathom
Author-email: nathanthomas707@gmail.com
Requires-Python: >=3.10,<4.0
Classifier: License :: OSI Approved :: GNU General Public License (GPL)
Classifier: License :: OSI Approved :: GNU General Public License v3 (GPLv3)
Classifier: Operating System :: OS Independent
Classifier: Programming Language :: Python :: 3
Classifier: Programming Language :: Python :: 3.10
Classifier: Programming Language :: Python :: 3.11
Classifier: Programming Language :: Python :: 3.12
Requires-Dist: Pillow (>=9,<11)
Requires-Dist: aiodns (>=3.0.0,<4.0.0)
Requires-Dist: aiofiles (>=0.7,<0.8)
Requires-Dist: aiohttp (>=3.9,<4.0)
Requires-Dist: aiolimiter (>=1.1.0,<2.0.0)
Requires-Dist: appdirs (>=1.4.4,<2.0.0)
Requires-Dist: click-help-colors (>=0.9.2,<0.10.0)
Requires-Dist: deezer-py (==1.3.6)
Requires-Dist: m3u8 (>=0.9.0,<0.10.0)
Requires-Dist: mutagen (>=1.45.1,<2.0.0)
Requires-Dist: pathvalidate (>=2.4.1,<3.0.0)
Requires-Dist: pick (>=2,<3) ; sys_platform == "win32" or sys_platform == "cygwin"
Requires-Dist: pycryptodomex (>=3.10.1,<4.0.0)
Requires-Dist: pytest-asyncio (>=0.21.1,<0.22.0)
Requires-Dist: pytest-mock (>=3.11.1,<4.0.0)
Requires-Dist: rich (>=13.6.0,<14.0.0)
Requires-Dist: simple-term-menu (>=1.2.1,<2.0.0) ; sys_platform == "darwin" or sys_platform == "linux"
Requires-Dist: tomlkit (>=0.7.2,<0.8.0)
Requires-Dist: windows-curses (>=2.2.0,<3.0.0) ; sys_platform == "win32" or sys_platform == "cygwin"
Project-URL: Bug Reports, https://github.com/nathom/streamrip/issues
Project-URL: Repository, https://github.com/nathom/streamrip
